{
    "23_05_2020_1302": {
        "Celsius": "67",
        "Moisture_level": "1023"
    },
    "23_05_2020_1304": {
        "Celsius": "65",
        "Moisture_level": "1023"
    },
    "23_05_2020_1308": {
        "Celsius": "79",
        "Moisture_level": "1023"
    },
    "23_05_2020_1310": {
        "Celsius": "77",
        "Moisture_level": "1023"
    },
    "23_05_2020_1413": {
        "Celsius": "83",
        "Moisture_level": "1023"
    },
    "23_05_2020_1438": {
        "Celsius": "65",
        "Moisture_level": "1023"
    },
    "23_05_2020_1439": {
        "Celsius": "60",
        "Moisture_level": "1023"
    }
}